examples/__init__.py
examples/controller_multihop/__init__.py
examples/controller_multihop/flow.py
examples/fanout_join/__init__.py
examples/fanout_join/flow.py
examples/map_concurrent/__init__.py
examples/map_concurrent/flow.py
examples/memory_basic/__init__.py
examples/memory_basic/flow.py
examples/memory_callbacks/__init__.py
examples/memory_callbacks/flow.py
examples/memory_custom/__init__.py
examples/memory_custom/flow.py
examples/memory_persistence/__init__.py
examples/memory_persistence/flow.py
examples/memory_redis/__init__.py
examples/memory_redis/flow.py
examples/memory_truncation/__init__.py
examples/memory_truncation/flow.py
examples/metadata_propagation/flow.py
examples/mlflow_metrics/__init__.py
examples/mlflow_metrics/flow.py
examples/planner_enterprise_agent/__init__.py
examples/planner_enterprise_agent/config.py
examples/planner_enterprise_agent/main.py
examples/planner_enterprise_agent/nodes.py
examples/planner_enterprise_agent/telemetry.py
examples/planner_enterprise_agent_v2/__init__.py
examples/planner_enterprise_agent_v2/config.py
examples/planner_enterprise_agent_v2/main.py
examples/planner_enterprise_agent_v2/nodes.py
examples/planner_enterprise_agent_v2/telemetry.py
examples/playbook_retrieval/__init__.py
examples/playbook_retrieval/flow.py
examples/policy_filtering/main.py
examples/quickstart/__init__.py
examples/quickstart/flow.py
examples/react_memory_context/main.py
examples/react_minimal/main.py
examples/react_parallel/main.py
examples/react_parallel_join/__init__.py
examples/react_parallel_join/main.py
examples/react_pause_resume/main.py
examples/react_replan/main.py
examples/react_typed_tools/__init__.py
examples/react_typed_tools/main.py
examples/reliability_middleware/__init__.py
examples/reliability_middleware/flow.py
examples/roadmap_status_updates/__init__.py
examples/roadmap_status_updates/flow.py
examples/roadmap_status_updates_subflows/__init__.py
examples/roadmap_status_updates_subflows/flow.py
penguiflow-2.10.1.dist-info/licenses/LICENSE
penguiflow-2.10.1.dist-info/METADATA
penguiflow-2.10.1.dist-info/WHEEL
penguiflow-2.10.1.dist-info/entry_points.txt
penguiflow-2.10.1.dist-info/top_level.txt
penguiflow-2.10.1.dist-info/RECORD
