Metadata-Version: 2.4
Name: penguiflow
Version: 2.10.1
Summary: Async-first orchestration library for multi-agent and data pipelines
Author: PenguiFlow Team
License: MIT License
Project-URL: Homepage, https://github.com/penguiflow/penguiflow
Requires-Python: >=3.11
License-File: LICENSE
Requires-Dist: pydantic>=2.6
Requires-Dist: click>=8.1
Requires-Dist: pyyaml>=6.0
Requires-Dist: fastapi>=0.118
Requires-Dist: uvicorn>=0.32
Provides-Extra: dev
Requires-Dist: mypy>=1.8; extra == "dev"
Requires-Dist: pytest>=7.4; extra == "dev"
Requires-Dist: pytest-asyncio>=0.23; extra == "dev"
Requires-Dist: pytest-cov>=4.0; extra == "dev"
Requires-Dist: coverage[toml]>=7.0; extra == "dev"
Requires-Dist: hypothesis>=6.103; extra == "dev"
Requires-Dist: ruff>=0.2; extra == "dev"
Requires-Dist: ag-ui-protocol>=0.0.42; extra == "dev"
Requires-Dist: jsonschema>=4.23; extra == "dev"
Requires-Dist: fastapi>=0.118; extra == "dev"
Requires-Dist: httpx>=0.27; extra == "dev"
Requires-Dist: jinja2>=3.1; extra == "dev"
Requires-Dist: pyyaml>=6.0; extra == "dev"
Requires-Dist: uvicorn>=0.32; extra == "dev"
Requires-Dist: tenacity>=9.0.0; extra == "dev"
Requires-Dist: aiohttp>=3.9.0; extra == "dev"
Requires-Dist: openai>=2.0.0; extra == "dev"
Requires-Dist: anthropic>=0.75.0; extra == "dev"
Requires-Dist: google-genai>=1.57.0; extra == "dev"
Requires-Dist: boto3>=1.42.0; extra == "dev"
Provides-Extra: cli
Requires-Dist: ag-ui-protocol>=0.0.42; extra == "cli"
Requires-Dist: jinja2>=3.1; extra == "cli"
Requires-Dist: fastapi>=0.118; extra == "cli"
Requires-Dist: uvicorn>=0.32; extra == "cli"
Provides-Extra: a2a-server
Requires-Dist: fastapi>=0.118; extra == "a2a-server"
Provides-Extra: planner
Requires-Dist: litellm>=1.77.3; extra == "planner"
Requires-Dist: dspy>=3.0.3; extra == "planner"
Requires-Dist: fastmcp>=2.13.0; extra == "planner"
Requires-Dist: utcp>=1.1.0; extra == "planner"
Requires-Dist: utcp-http>=1.0.0; extra == "planner"
Requires-Dist: tenacity>=9.0.0; extra == "planner"
Requires-Dist: aiohttp>=3.9.0; extra == "planner"
Requires-Dist: jsonschema>=4.23; extra == "planner"
Provides-Extra: llm
Requires-Dist: openai>=2.0.0; extra == "llm"
Requires-Dist: anthropic>=0.75.0; extra == "llm"
Requires-Dist: google-genai>=1.57.0; extra == "llm"
Requires-Dist: boto3>=1.42.0; extra == "llm"
Requires-Dist: databricks-sdk>=0.77.0; extra == "llm"
Provides-Extra: tools-cli
Requires-Dist: utcp-cli>=1.0.0; extra == "tools-cli"
Provides-Extra: tools-websocket
Requires-Dist: utcp-websocket>=1.0.0; extra == "tools-websocket"
Dynamic: license-file
